webanno2spacy/__init__.py
webanno2spacy-0.1.0.dist-info/METADATA
webanno2spacy-0.1.0.dist-info/WHEEL
webanno2spacy-0.1.0.dist-info/entry_points.txt
webanno2spacy-0.1.0.dist-info/RECORD
