Metadata-Version: 2.1
Name: webanno2spacy
Version: 0.1.0
Summary: A tool to convert WebAnno v3.x TSV files into spaCy v3.x Doc format.
License: Apache-2.0
Author: Ilya Nikitin
Author-email: ilya.i.nikitin@proton.me
Requires-Python: >=3.10,<4.0
Classifier: License :: OSI Approved :: Apache Software License
Classifier: Programming Language :: Python :: 3
Classifier: Programming Language :: Python :: 3.10
Classifier: Programming Language :: Python :: 3.11
Classifier: Programming Language :: Python :: 3.12
Requires-Dist: spacy (>=3.7,<4.0)
